nevolve/__init__.py
nevolve/envs/__init__.py
nevolve/envs/bipedal_walker_v2.py
nevolve/envs/cart_pole_v0.py
nevolve/envs/mountain_car_v0.py
nevolve/evolve/__init__.py
nevolve/evolve/population.py
nevolve/neuro/__init__.py
nevolve/neuro/activations.py
nevolve/neuro/dnn.py
nevolve/neuro/nn.py
nevolve-0.1.0.dist-info/LICENSE
nevolve-0.1.0.dist-info/METADATA
nevolve-0.1.0.dist-info/WHEEL
nevolve-0.1.0.dist-info/top_level.txt
nevolve-0.1.0.dist-info/RECORD
