Metadata-Version: 2.1
Name: nevolve
Version: 0.1.0
Summary: Neuro-Evolution Library for Reinforcement Learning.
Home-page: https://github.com/kaustubholpadkar/nevolve
Author: Kaustubh Olpadkar
Author-email: UNKNOWN
License: UNKNOWN
Keywords: neuroevolution machine-learning neural-networks
Platform: UNKNOWN
